[
    {
        "Offers": "Any Pepsi Beverages",
        "Buy": "$1 ",
        "Get": "200"
    },
    {
        "Offers": "Apples",
        "Buy": "$1 ",
        "Get": "200"
    },
    {
        "Offers": "Colgate Oral Care Products",
        "Buy": "$4 ",
        "Get": "800"
    },
    {
        "Offers": "Deli Meat Including Service Counter",
        "Buy": "$1 ",
        "Get": "200"
    },
    {
        "Offers": "D'italiano Products",
        "Buy": "$2 ",
        "Get": "400"
    },
    {
        "Offers": "Fresh Beef",
        "Buy": "$1 ",
        "Get": "200"
    },
    {
        "Offers": "Gadoua Bread",
        "Buy": "$2 ",
        "Get": "400"
    },
    {
        "Offers": "Grapes",
        "Buy": "$1 ",
        "Get": "200"
    },
    {
        "Offers": "Herbal Essences",
        "Buy": "$3 ",
        "Get": "600"
    },
    {
        "Offers": "Hygrade Weiners",
        "Buy": "$4 ",
        "Get": "200"
    },
    {
        "Offers": "Iceberg Lettuce",
        "Get": "300"
    },
    {
        "Offers": "L Extra Camembert",
        "Get": "1,000"
    },
    {
        "Offers": "Lactantcia Butter or Margarine",
        "Buy": "$3 ",
        "Get": "600"
    },
    {
        "Offers": "Lemons",
        "Buy": "$1 ",
        "Get": "200"
    },
    {
        "Offers": "Life Brand Epsom Salts",
        "Buy": "$1 ",
        "Get": "200"
    },
    {
        "Offers": "Life Brand Toothbrush of Floss products",
        "Buy": "$1 ",
        "Get": "200"
    },
    {
        "Offers": "no name Baking Coconut",
        "Buy": "$1 ",
        "Get": "200"
    },
    {
        "Offers": "no name Butter",
        "Buy": "$3 ",
        "Get": "600"
    },
    {
        "Offers": "no name Canned Chicken or Beef Broth",
        "Buy": "$1 ",
        "Get": "200"
    },
    {
        "Offers": "no name Food Storage Containers",
        "Buy": "$2 ",
        "Get": "400"
    },
    {
        "Offers": "no name Garbage Bags",
        "Buy": "$4 ",
        "Get": "800"
    },
    {
        "Offers": "no name Plastic Wrap",
        "Buy": "$3 ",
        "Get": "600"
    },
    {
        "Offers": "Nong Shim Instant Noodles",
        "Get": "200"
    },
    {
        "Offers": "Oranges",
        "Buy": "$1 ",
        "Get": "200"
    },
    {
        "Offers": "PC Batteries",
        "Buy": "$1 ",
        "Get": "200"
    },
    {
        "Offers": "PC Blue Menu Eggs",
        "Buy": "$3 ",
        "Get": "600"
    },
    {
        "Offers": "PC Blue Menu Peanut Butter",
        "Buy": "$2 ",
        "Get": "400"
    },
    {
        "Offers": "PC Blue Menu Popcorn",
        "Buy": "$1 ",
        "Get": "200"
    },
    {
        "Offers": "PC Cereal",
        "Buy": "$3 ",
        "Get": "600"
    },
    {
        "Offers": "PC Chocolate",
        "Buy": "$3 ",
        "Get": "600"
    },
    {
        "Offers": "PC Cookies",
        "Get": "600"
    },
    {
        "Offers": "PC Fabric Softener or Dryer Sheets",
        "Buy": "$2 ",
        "Get": "400"
    },
    {
        "Offers": "PC Frozen Beef Burgers",
        "Buy": "$9 ",
        "Get": "1,800"
    },
    {
        "Offers": "PC Frozen Fish",
        "Buy": "$8 ",
        "Get": "1,600"
    },
    {
        "Offers": "PC Frozen Pizza",
        "Buy": "$4 ",
        "Get": "800"
    },
    {
        "Offers": "PC Granola Bars",
        "Buy": "$2 ",
        "Get": "400"
    },
    {
        "Offers": "PC Household Cleaners",
        "Buy": "$2 ",
        "Get": "400"
    },
    {
        "Offers": "PC Liquid Soap products",
        "Buy": "$2 ",
        "Get": "400"
    },
    {
        "Offers": "PC or no name Ready to Serve Soup",
        "Buy": "$1 ",
        "Get": "200"
    },
    {
        "Offers": "PC Packaged Mushrooms",
        "Buy": "$2 ",
        "Get": "400"
    },
    {
        "Offers": "PC Pork Ribs",
        "Get": "2,200"
    },
    {
        "Offers": "PC Roast or Ground Coffee",
        "Buy": "$6 ",
        "Get": "1,200"
    },
    {
        "Offers": "PC Soft Drinks and Sparkling Soda",
        "Buy": "$2 ",
        "Get": "400"
    },
    {
        "Offers": "Potatoes",
        "Buy": "$1 ",
        "Get": "200"
    },
    {
        "Offers": "Rooster Luncheon Meat",
        "Buy": "$1 ",
        "Get": "200"
    },
    {
        "Offers": "Rooster Rice",
        "Buy": "$2 ",
        "Get": "400"
    },
    {
        "Offers": "Tomatoes",
        "Buy": "$1 ",
        "Get": "200"
    },
    {
        "Offers": "Tostitos Tortilla Chips or Salsa",
        "Get": "600"
    },
    {
        "Offers": "Ziploc Bags",
        "Buy": "$3 ",
        "Get": "600"
    }
]